cadquery/README.txt
cadquery/__init__.py
cadquery/assembly.py
cadquery/cq.py
cadquery/cq_directive.py
cadquery/cqgi.py
cadquery/func.py
cadquery/hull.py
cadquery/py.typed
cadquery/selectors.py
cadquery/sketch.py
cadquery/types.py
cadquery/units.py
cadquery/utils.py
cadquery/vis.py
cadquery/contrib/__init__.py
cadquery/occ_impl/README.txt
cadquery/occ_impl/__init__.py
cadquery/occ_impl/assembly.py
cadquery/occ_impl/geom.py
cadquery/occ_impl/jupyter_tools.py
cadquery/occ_impl/shape_protocols.py
cadquery/occ_impl/shapes.py
cadquery/occ_impl/sketch_solver.py
cadquery/occ_impl/solver.py
cadquery/occ_impl/exporters/__init__.py
cadquery/occ_impl/exporters/amf.py
cadquery/occ_impl/exporters/assembly.py
cadquery/occ_impl/exporters/dxf.py
cadquery/occ_impl/exporters/json.py
cadquery/occ_impl/exporters/svg.py
cadquery/occ_impl/exporters/threemf.py
cadquery/occ_impl/exporters/vtk.py
cadquery/occ_impl/importers/__init__.py
cadquery/occ_impl/importers/dxf.py
cadquery/plugins/__init__.py
cadquery-2.5.1.dist-info/LICENSE
cadquery-2.5.1.dist-info/METADATA
cadquery-2.5.1.dist-info/WHEEL
cadquery-2.5.1.dist-info/top_level.txt
cadquery-2.5.1.dist-info/RECORD
