Metadata-Version: 2.1
Name: cadquery
Version: 2.5.1
Summary: CadQuery is a parametric  scripting language for creating and traversing CAD models
Home-page: https://github.com/CadQuery/cadquery
Author: David Cowden
Author-email: dave.cowden@gmail.com
License: Apache Public License 2.0
Platform: any
Classifier: Development Status :: 5 - Production/Stable
Classifier: Intended Audience :: Developers
Classifier: Intended Audience :: End Users/Desktop
Classifier: Intended Audience :: Information Technology
Classifier: Intended Audience :: Science/Research
Classifier: Intended Audience :: System Administrators
Classifier: License :: OSI Approved :: Apache Software License
Classifier: Operating System :: POSIX
Classifier: Operating System :: MacOS
Classifier: Operating System :: Unix
Classifier: Programming Language :: Python
Classifier: Topic :: Software Development :: Libraries :: Python Modules
Classifier: Topic :: Internet
Classifier: Topic :: Scientific/Engineering
Requires-Python: >=3.9
License-File: LICENSE
Provides-Extra: dev
Requires-Dist: docutils; extra == "dev"
Requires-Dist: ipython; extra == "dev"
Requires-Dist: pytest; extra == "dev"
Provides-Extra: ipython
Requires-Dist: ipython; extra == "ipython"
